tm4j_reporter_api/tm4j_api/__init__.py
tm4j_reporter_api/tm4j_api/tm4j_api.py
tm4j_reporter_api/tm4j_configuration/__init__.py
tm4j_reporter_api/tm4j_configuration/tm4j_configuration.py
tm4j_reporter_api/tm4j_exceptions/__init__.py
tm4j_reporter_api/tm4j_exceptions/tm4j_configuration_exceptions.py
tm4j_reporter_api/tm4j_exceptions/tm4j_response_exceptions.py
tm4j_reporter_api-0.1.2.dist-info/LICENSE
tm4j_reporter_api-0.1.2.dist-info/METADATA
tm4j_reporter_api-0.1.2.dist-info/WHEEL
tm4j_reporter_api-0.1.2.dist-info/top_level.txt
tm4j_reporter_api-0.1.2.dist-info/RECORD
