Metadata-Version: 2.1
Name: tm4j-reporter-api
Version: 0.1.2
Summary: python package providing functionality for Jira Test Management (tm4j) Cloud through REST API calls
Home-page: https://github.com/Klika-Tech/tm4j_reporter_api
Author: Klika-Tech, Inc
Author-email: contact@klika-tech.com
License: MIT
Keywords: python tm4j jira test testmanagement report
Platform: any
Classifier: Intended Audience :: Developers
Classifier: License :: OSI Approved :: MIT License
Classifier: Operating System :: OS Independent
Classifier: Programming Language :: Python
Classifier: Programming Language :: Python :: 3
Classifier: Topic :: Software Development :: Quality Assurance
Classifier: Topic :: Software Development :: Testing
Classifier: Topic :: Utilities
Classifier: Topic :: Software Development :: Libraries :: Python Modules
Requires-Python: >=3.6
Requires-Dist: requests
